{
  "CollectionCitations" : [ {
    "Creator" : "Charles Gatebe; Michael King; Rajesh Poudyal",
    "Title" : "CAR Kuwait Oil Fire Spectral Reflectance L1 V1",
    "SeriesName" : "CAR_KUWAITOILFIRE_L1C",
    "ReleaseDate" : "2018-01-10T00:00:00.000Z",
    "ReleasePlace" : "Greenbelt, MD, USA",
    "Publisher" : "Goddard Earth Sciences Data and Information Services Center (GES DISC)",
    "Version" : "1",
    "OnlineResource" : {
      "Linkage" : "https://disc.gsfc.nasa.gov/datacollection/CAR_KUWAITOILFIRE_L1C_1.html"
    }
  } ],
  "SpatialExtent" : {
    "GranuleSpatialRepresentation" : "CARTESIAN",
    "HorizontalSpatialDomain" : {
      "Geometry" : {
        "CoordinateSystem" : "CARTESIAN",
        "BoundingRectangles" : [ {
          "WestBoundingCoordinate" : 46.9617,
          "NorthBoundingCoordinate" : 28.7545,
          "EastBoundingCoordinate" : 50.7998,
          "SouthBoundingCoordinate" : 26.2602
        } ]
      }
    }
  },
  "CollectionProgress" : "COMPLETE",
  "ScienceKeywords" : [ {
    "Category" : "EARTH SCIENCE",
    "Topic" : "ATMOSPHERE",
    "Term" : "AEROSOLS",
    "VariableLevel1" : "AEROSOL RADIANCE"
  }, {
    "Category" : "EARTH SCIENCE",
    "Topic" : "ATMOSPHERE",
    "Term" : "CLOUDS",
    "VariableLevel1" : "CLOUD PROPERTIES"
  }, {
    "Category" : "EARTH SCIENCE",
    "Topic" : "ATMOSPHERE",
    "Term" : "ATMOSPHERIC RADIATION",
    "VariableLevel1" : "REFLECTANCE"
  }, {
    "Category" : "EARTH SCIENCE",
    "Topic" : "LAND SURFACE",
    "Term" : "SURFACE RADIATIVE PROPERTIES",
    "VariableLevel1" : "REFLECTANCE"
  }, {
    "Category" : "EARTH SCIENCE",
    "Topic" : "OCEANS",
    "Term" : "OCEAN OPTICS",
    "VariableLevel1" : "REFLECTANCE"
  } ],
  "TemporalExtents" : [ {
    "RangeDateTimes" : [ {
      "BeginningDateTime" : "1991-05-18T00:00:00.000Z",
      "EndingDateTime" : "1991-06-02T23:59:59.999Z"
    } ],
    "EndsAtPresentFlag" : false
  } ],
  "ProcessingLevel" : {
    "Id" : "1"
  },
  "DOI" : {
    "DOI" : "10.5067/CAR/DATA115"
  },
  "ShortName" : "CAR_KUWAITOILFIRE_L1C",
  "EntryTitle" : "CAR Kuwait Oil Fire Spectral Reflectance L1 V1 (CAR_KUWAITOILFIRE_L1C) at GES DISC",
  "PublicationReferences" : [ {
    "Author" : "Charles K. Gatebe and Michael D. King",
    "PublicationDate" : "2016-01-01T00:00:00.000Z",
    "Title" : "Airborne spectral BRDF of various surface types (ocean, vegetation, snow, desert, wetlands, cloud decks, smoke layers) for remote sensing applications"
  } ],
  "ISOTopicCategories" : [ "CLIMATOLOGY/METEOROLOGY/ATMOSPHERE" ],
  "RelatedUrls" : [ {
    "URL" : "https://docserver.gesdisc.eosdis.nasa.gov/public/project/Images/CAR_KUWAITOILFIRE_L1C_1.jpg",
    "URLContentType" : "VisualizationURL",
    "Type" : "GET RELATED VISUALIZATION"
  }, {
    "Type" : "DATA SET LANDING PAGE",
    "URL" : "https://disc.gsfc.nasa.gov/datacollection/CAR_KUWAITOILFIRE_L1C_1.html",
    "Description" : "Access the dataset landing page from the GES DISC website.",
    "URLContentType" : "CollectionURL"
  }, {
    "Type" : "GET DATA",
    "Subtype" : "DATA TREE",
    "URL" : "https://acdisc.gesdisc.eosdis.nasa.gov/data/CAR/CAR_KUWAITOILFIRE_L1C.1/",
    "Description" : "Access the data via HTTPS.",
    "URLContentType" : "DistributionURL"
  }, {
    "Type" : "USE SERVICE API",
    "Subtype" : "OPENDAP DATA",
    "URL" : "https://acdisc.gsfc.nasa.gov/opendap/CAR/CAR_KUWAITOILFIRE_L1C.1/contents.html",
    "Description" : "Access the data via the OPeNDAP protocol.",
    "URLContentType" : "DistributionURL"
  }, {
    "Type" : "PROJECT HOME PAGE",
    "URL" : "https://car.gsfc.nasa.gov/",
    "Description" : "CAR Project Home Page",
    "URLContentType" : "CollectionURL"
  }, {
    "Type" : "VIEW RELATED INFORMATION",
    "Subtype" : "READ-ME",
    "URL" : "https://acdisc.gesdisc.eosdis.nasa.gov/data/CAR/CAR_KUWAITOILFIRE_L1C.1/doc/CAR_README.pdf",
    "Description" : "README Document",
    "URLContentType" : "PublicationURL"
  } ],
  "DataDates" : [ {
    "Date" : "2017-11-29T00:00:00.000Z",
    "Type" : "CREATE"
  }, {
    "Date" : "2017-11-29T00:00:00.000Z",
    "Type" : "UPDATE"
  } ],
  "Abstract" : "CAR Kuwait Oil Fire mission measured bidirectional reflectance function of smoke from Kuwait oil fires during the Kuwait Oil Fire Smoke Experiment. Measurements were also taken over the Saudi Arabian desert with overlying desert dust, and Persian Gulf waters with some overlying aerosols.",
  "LocationKeywords" : [ {
    "Category" : "CONTINENT",
    "Type" : "ASIA",
    "Subregion1" : "WESTERN ASIA",
    "Subregion2" : "MIDDLE EAST",
    "Subregion3" : "KUWAIT"
  }, {
    "Category" : "CONTINENT",
    "Type" : "ASIA",
    "Subregion1" : "WESTERN ASIA",
    "Subregion2" : "MIDDLE EAST",
    "Subregion3" : "SAUDI ARABIA"
  } ],
  "MetadataDates" : [ {
    "Date" : "2017-08-11T00:00:00.000Z",
    "Type" : "CREATE"
  }, {
    "Date" : "2018-09-26T00:00:00.000Z",
    "Type" : "UPDATE"
  } ],
  "Version" : "1",
  "Projects" : [ {
    "ShortName" : "CAR",
    "LongName" : "Cloud Absorption Radiometer"
  } ],
  "UseConstraints" : {
    "Description" : "The Earth Observing System Data and Information System (EOSDIS) data use policy for NASA data can be accessed at https://earthdata.nasa.gov/earth-observation-data/data-use-policy. For information on how to properly cite and acknowledge data from the NASA GES DISC, refer to https://disc.gsfc.nasa.gov/information/documents?title=data-policy."
  },
  "ContactPersons" : [ {
    "Roles" : [ "Investigator" ],
    "FirstName" : "CHARLES",
    "LastName" : "GATEBE",
    "ContactInformation" : {
      "ContactMechanisms" : [ {
        "Type" : "Telephone",
        "Value" : "301-614-6228"
      }, {
        "Type" : "Email",
        "Value" : "gatebe@climate.gsfc.nasa.gov"
      } ]
    }
  }, {
    "Roles" : [ "Metadata Author" ],
    "FirstName" : "ELLIOT",
    "LastName" : "SHERMAN",
    "ContactInformation" : {
      "Addresses" : [ {
        "StreetAddresses" : [ "Goddard Earth Sciences Data and Information Services Center, Code 610.2, NASA Goddard Space Flight Center" ],
        "City" : "Greenbelt",
        "StateProvince" : "MD",
        "PostalCode" : "20771",
        "Country" : "USA"
      } ],
      "ContactMechanisms" : [ {
        "Type" : "Telephone",
        "Value" : "301-614-6492"
      }, {
        "Type" : "Email",
        "Value" : "elliot.m.sherman@nasa.gov"
      } ]
    }
  } ],
  "DataCenters" : [ {
    "Roles" : [ "ARCHIVER" ],
    "ShortName" : "NASA/GSFC/SED/ESD/GCDC/GESDISC",
    "LongName" : "Goddard Earth Sciences Data and Information Services Center (formerly Goddard DAAC), Global Change Data Center, Earth Sciences Division, Science and Exploration Directorate, Goddard Space Flight Center, NASA",
    "ContactInformation" : {
      "RelatedUrls" : [ {
        "URLContentType" : "DataCenterURL",
        "Type" : "HOME PAGE",
        "URL" : "https://disc.gsfc.nasa.gov/",
        "Description" : "NASA GES DISC Website"
      } ]
    },
    "ContactGroups" : [ {
      "Roles" : [ "Data Center Contact" ],
      "GroupName" : "GES DISC HELP DESK SUPPORT GROUP",
      "ContactInformation" : {
        "Addresses" : [ {
          "StreetAddresses" : [ "Goddard Earth Sciences Data and Information Services Center", "Code 610.2", "NASA Goddard Space Flight Center" ],
          "City" : "Greenbelt",
          "StateProvince" : "MD",
          "PostalCode" : "20771",
          "Country" : "USA"
        } ],
        "ContactMechanisms" : [ {
          "Type" : "Telephone",
          "Value" : "301-614-5224"
        }, {
          "Type" : "Fax",
          "Value" : "301-614-5268"
        }, {
          "Type" : "Email",
          "Value" : "gsfc-dl-help-disc@mail.nasa.gov"
        } ]
      }
    } ]
  } ],
  "Platforms" : [ {
    "Type" : "Aircraft",
    "ShortName" : "C-131A",
    "LongName" : "Convair C-131 Samaritan",
    "Instruments" : [ {
      "ShortName" : "CAR",
      "LongName" : "Cloud Absorption Radiometer"
    } ]
  } ],
  "ArchiveAndDistributionInformation" : {
    "FileDistributionInformation" : [ {
      "FormatType" : "Native",
      "Media" : [ "Online Archive" ],
      "Format" : "netCDF",
      "Fees" : "None"
    } ]
  }
}