{
  "DataLanguage" : "English",
  "CollectionCitations" : [ {
    "Creator" : "Joanna Joiner",
    "DataPresentationForm" : "Digital Science Data",
    "OnlineResource" : {
      "Linkage" : "https://disc.gsfc.nasa.gov/datacollection/OMPS_NPP_NMCLDRR_L2_2.html"
    },
    "Publisher" : "Goddard Earth Sciences Data and Information Services Center (GES DISC)",
    "Title" : "OMPS-NPP L2 NM Cloud Pressure and Fraction swath orbital V2",
    "SeriesName" : "OMPS_NPP_NMCLDRR_L2",
    "ReleaseDate" : "2020-02-26T00:00:00.000Z",
    "Version" : "2",
    "ReleasePlace" : "Greenbelt, MD, USA"
  } ],
  "SpatialExtent" : {
    "GranuleSpatialRepresentation" : "GEODETIC",
    "HorizontalSpatialDomain" : {
      "Geometry" : {
        "CoordinateSystem" : "CARTESIAN",
        "BoundingRectangles" : [ {
          "WestBoundingCoordinate" : -180,
          "NorthBoundingCoordinate" : 90,
          "EastBoundingCoordinate" : 180,
          "SouthBoundingCoordinate" : -90
        } ]
      }
    }
  },
  "CollectionProgress" : "ACTIVE",
  "ScienceKeywords" : [ {
    "Category" : "EARTH SCIENCE",
    "Topic" : "ATMOSPHERE",
    "Term" : "CLOUDS",
    "VariableLevel1" : "CLOUD PROPERTIES",
    "VariableLevel2" : "CLOUD FRACTION"
  }, {
    "Category" : "EARTH SCIENCE",
    "Topic" : "ATMOSPHERE",
    "Term" : "CLOUDS",
    "VariableLevel1" : "CLOUD PROPERTIES",
    "VariableLevel2" : "CLOUD TOP PRESSURE"
  } ],
  "TemporalExtents" : [ {
    "RangeDateTimes" : [ {
      "BeginningDateTime" : "2011-11-13T00:00:00.000Z"
    } ],
    "EndsAtPresentFlag" : true
  } ],
  "ProcessingLevel" : {
    "Id" : "2"
  },
  "DOI" : {
    "DOI" : "10.5067/CJAALTQUCLO2"
  },
  "ShortName" : "OMPS_NPP_NMCLDRR_L2",
  "EntryTitle" : "OMPS-NPP L2 NM Cloud Pressure and Fraction swath orbital V2 (OMPS_NPP_NMCLDRR_L2) at GES DISC",
  "PublicationReferences" : [ {
    "Author" : "Joiner, J., and A. P. Vasilkov",
    "PublicationDate" : "2006-01-01T00:00:00.000Z",
    "Title" : "First results from the OMI Rotational Raman Scattering Cloud Pressure Algorithm",
    "Volume" : "44",
    "Publisher" : "IEEE Trans. Geosci. Rem. Sens.",
    "Pages" : "1272-1282",
    "DOI" : {
      "DOI" : "10.1109/TGRS.2005.861385"
    }
  } ],
  "ISOTopicCategories" : [ "CLIMATOLOGY/METEOROLOGY/ATMOSPHERE" ],
  "RelatedUrls" : [ {
    "URL" : "https://docserver.gesdisc.eosdis.nasa.gov/public/project/Images/OMPS_NPP_NMCLDRR_L2_2.jpeg",
    "URLContentType" : "VisualizationURL",
    "Type" : "GET RELATED VISUALIZATION"
  }, {
    "Type" : "DATA SET LANDING PAGE",
    "URL" : "https://disc.gsfc.nasa.gov/datacollection/OMPS_NPP_NMCLDRR_L2_2.html",
    "Description" : "Access the dataset landing page from the GES DISC website.",
    "URLContentType" : "CollectionURL"
  }, {
    "Type" : "GET DATA",
    "Subtype" : "DATA TREE",
    "URL" : "https://omps.gesdisc.eosdis.nasa.gov/data/SNPP_OMPS_Level2/OMPS_NPP_NMCLDRR_L2.2/",
    "Description" : "Access the data via HTTPS.",
    "URLContentType" : "DistributionURL"
  }, {
    "Type" : "USE SERVICE API",
    "Subtype" : "OPENDAP DATA",
    "URL" : "https://omps.gesdisc.eosdis.nasa.gov/opendap/SNPP_OMPS_Level2/OMPS_NPP_NMCLDRR_L2.2/contents.html",
    "Description" : "Access the data via the OPeNDAP protocol.",
    "URLContentType" : "DistributionURL"
  }, {
    "Type" : "GET DATA",
    "Subtype" : "Earthdata Search",
    "URL" : "https://search.earthdata.nasa.gov/search?q=OMPS_NPP_NMCLDRR_L2_2",
    "Description" : "Use the Earthdata Search to find and retrieve data sets across multiple data centers.",
    "URLContentType" : "DistributionURL"
  }, {
    "Type" : "VIEW RELATED INFORMATION",
    "Subtype" : "READ-ME",
    "URL" : "https://omps.gesdisc.eosdis.nasa.gov/data/SNPP_OMPS_Level2/OMPS_NPP_NMCLDRR_L2.2/doc/README.OMPS_NPP_NMCLDRR_L2.pdf",
    "Description" : "README Document",
    "URLContentType" : "PublicationURL"
  }, {
    "Type" : "PROJECT HOME PAGE",
    "URL" : "https://jointmission.gsfc.nasa.gov/",
    "Description" : "Joint Polar Satellite System (JPSS) mission home page",
    "URLContentType" : "CollectionURL"
  } ],
  "DataDates" : [ {
    "Date" : "2020-02-26T00:00:00.000Z",
    "Type" : "CREATE"
  }, {
    "Date" : "2020-02-26T00:00:00.000Z",
    "Type" : "UPDATE"
  } ],
  "Abstract" : "The OMPS-NPP L2 NM Cloud Pressure and Fraction swath orbital product provides effective cloud fraction and effective cloud pressure retrievals from the Ozone Mapping and Profiling Suite (OMPS) Nadir-Mapper (NM) instrument on the Suomi-NPP satellite. The cloud pressure algorithm retrieves effective cloud pressus, a.k.a optical centroid pressure (OCP) and effective cloud fraction (ECF) using a concept of Mixed Lambert Equivalent Reflectivity (MLER) at 354.1 nm.\n\nEach granule contains data from the daylight portion of each orbit measured for a full day. Spatial coverage is global (-90 to  90 degrees latitude), and there are about 14.5 orbits per day each measuring three limb profiles spaced approximately 250 km in the cross-track direction. The profiles are measured from the ground up to about 80 km with a vertical resolution of the retrieved profiles of approximately 1.8 km.\n\nThe files are written using the Hierarchical Data Format Version 5 or HDF5.",
  "LocationKeywords" : [ {
    "Category" : "GEOGRAPHIC REGION",
    "Type" : "GLOBAL"
  } ],
  "MetadataDates" : [ {
    "Date" : "2020-02-26T00:00:00.000Z",
    "Type" : "CREATE"
  }, {
    "Date" : "2020-02-26T00:00:00.000Z",
    "Type" : "UPDATE"
  } ],
  "Version" : "2",
  "Projects" : [ {
    "ShortName" : "NPP-JPSS",
    "LongName" : "National Polar Orbiting Partnership-Joint Polar Satellite System"
  } ],
  "UseConstraints" : {
    "Description" : "The Earth Observing System Data and Information System (EOSDIS) data use policy for NASA data can be accessed at https://earthdata.nasa.gov/earth-observation-data/data-use-policy. For information on how to properly cite and acknowledge data from the NASA GES DISC, refer to https://disc.gsfc.nasa.gov/information/documents?title=data-policy."
  },
  "ContactPersons" : [ {
    "Roles" : [ "Investigator" ],
    "FirstName" : "JOANNA",
    "LastName" : "JOINER, PH. D",
    "ContactInformation" : {
      "Addresses" : [ {
        "StreetAddresses" : [ "NASA Goddard Space Flight Center, Code 613.3, Bldg 33" ],
        "City" : "Greenbelt",
        "StateProvince" : "MD",
        "PostalCode" : "20771",
        "Country" : "USA"
      } ],
      "ContactMechanisms" : [ {
        "Type" : "Telephone",
        "Value" : "301-614-6247"
      }, {
        "Type" : "Email",
        "Value" : "Joanna.Joiner@nasa.gov"
      } ]
    }
  }, {
    "Roles" : [ "Metadata Author" ],
    "FirstName" : "JAMES",
    "MiddleName" : "EDWARD",
    "LastName" : "JOHNSON",
    "ContactInformation" : {
      "Addresses" : [ {
        "StreetAddresses" : [ "NASA Goddard Space Flight Center", "Code 610.2" ],
        "City" : "Greenbelt",
        "StateProvince" : "MD",
        "PostalCode" : "20771",
        "Country" : "USA"
      } ],
      "ContactMechanisms" : [ {
        "Type" : "Telephone",
        "Value" : "301-614-5121"
      }, {
        "Type" : "Email",
        "Value" : "James.Johnson@nasa.gov"
      } ]
    }
  } ],
  "CollectionDataType" : "SCIENCE_QUALITY",
  "DataCenters" : [ {
    "Roles" : [ "ARCHIVER" ],
    "ShortName" : "NASA/GSFC/SED/ESD/GCDC/GESDISC",
    "LongName" : "Goddard Earth Sciences Data and Information Services Center (formerly Goddard DAAC), Global Change Data Center, Earth Sciences Division, Science and Exploration Directorate, Goddard Space Flight Center, NASA",
    "ContactInformation" : {
      "RelatedUrls" : [ {
        "URLContentType" : "DataCenterURL",
        "Type" : "HOME PAGE",
        "URL" : "https://disc.gsfc.nasa.gov/",
        "Description" : "NASA GES DISC Website"
      } ]
    },
    "ContactGroups" : [ {
      "Roles" : [ "Data Center Contact" ],
      "GroupName" : "GES DISC HELP DESK SUPPORT GROUP",
      "ContactInformation" : {
        "Addresses" : [ {
          "StreetAddresses" : [ "Goddard Earth Sciences Data and Information Services Center", "Code 610.2", "NASA Goddard Space Flight Center" ],
          "City" : "Greenbelt",
          "StateProvince" : "MD",
          "PostalCode" : "20771",
          "Country" : "USA"
        } ],
        "ContactMechanisms" : [ {
          "Type" : "Telephone",
          "Value" : "301-614-5224"
        }, {
          "Type" : "Fax",
          "Value" : "301-614-5268"
        }, {
          "Type" : "Email",
          "Value" : "gsfc-dl-help-disc@mail.nasa.gov"
        } ]
      }
    } ]
  } ],
  "Platforms" : [ {
    "Type" : "Earth Observation Satellites",
    "ShortName" : "SUOMI-NPP",
    "LongName" : "Suomi National Polar-orbiting Partnership",
    "Instruments" : [ {
      "ShortName" : "OMPS",
      "LongName" : "Ozone Mapping and Profiler Suite"
    } ]
  } ],
  "ArchiveAndDistributionInformation" : {
    "FileDistributionInformation" : [ {
      "FormatType" : "Native",
      "Media" : [ "Online Archive" ],
      "Format" : "HDF5",
      "Fees" : "None"
    } ]
  }
}