{
  "DataLanguage" : "English",
  "AncillaryKeywords" : [ "EOSDIS" ],
  "CollectionCitations" : [ {
    "Creator" : "Tropical Rainfall Measuring Mission (TRMM)",
    "Title" : "TRMM Precipitation Radar Power and Reflectivity L1 1.5 hours V7",
    "SeriesName" : "TRMM_1C21",
    "ReleaseDate" : "2011-07-01T00:00:00.000Z",
    "ReleasePlace" : "Greenbelt, MD",
    "Publisher" : "Goddard Earth Sciences Data and Information Services Center (GES DISC)",
    "OnlineResource" : {
      "Linkage" : "https://disc.gsfc.nasa.gov/datacollection/TRMM_1C21_7.html"
    }
  } ],
  "SpatialExtent" : {
    "GranuleSpatialRepresentation" : "CARTESIAN",
    "HorizontalSpatialDomain" : {
      "Geometry" : {
        "CoordinateSystem" : "CARTESIAN",
        "BoundingRectangles" : [ {
          "WestBoundingCoordinate" : -180,
          "NorthBoundingCoordinate" : 38,
          "EastBoundingCoordinate" : 180,
          "SouthBoundingCoordinate" : -38
        } ]
      }
    }
  },
  "CollectionProgress" : "COMPLETE",
  "ScienceKeywords" : [ {
    "Category" : "EARTH SCIENCE",
    "Topic" : "SPECTRAL/ENGINEERING",
    "Term" : "RADAR",
    "VariableLevel1" : "RADAR BACKSCATTER"
  }, {
    "Category" : "EARTH SCIENCE",
    "Topic" : "SPECTRAL/ENGINEERING",
    "Term" : "RADAR",
    "VariableLevel1" : "RADAR REFLECTIVITY"
  } ],
  "TemporalExtents" : [ {
    "RangeDateTimes" : [ {
      "BeginningDateTime" : "1997-12-07T00:00:00.000Z",
      "EndingDateTime" : "2015-04-01T23:59:59.999Z"
    } ],
    "EndsAtPresentFlag" : false
  } ],
  "ProcessingLevel" : {
    "Id" : "1"
  },
  "DOI" : {
    "MissingReason" : "Not Applicable",
    "Explanation" : "Legacy dataset"
  },
  "ShortName" : "TRMM_1C21",
  "EntryTitle" : "TRMM Precipitation Radar Power and Reflectivity L1C 1.5 hours V7 (TRMM_1C21) at GES DISC",
  "PublicationReferences" : [ {
    "Author" : "Taylor I.J., G.M. Heymsfield, R. Meneghini, and L.S. Miller",
    "PublicationDate" : "1997-01-01T00:00:00.000Z",
    "Title" : "Correction of sampling errors in ocean surface cross-sectional estimates from nadir-looking  weather radar.",
    "Series" : "J. Atmos. Oceanic Technol",
    "Volume" : "14",
    "Pages" : "203-210"
  }, {
    "Author" : "Iguchi, T. and R. Meneghini",
    "PublicationDate" : "1994-01-01T00:00:00.000Z",
    "Title" : "Intercomparisons of single-frequency methods for retrieving a vertical rain profile from airborne or spaceborne radar data.",
    "Series" : "J. Atmos. Oceanic Technol.",
    "Volume" : "11",
    "Pages" : "1507-1516"
  }, {
    "Author" : "Kozu, T.",
    "PublicationDate" : "1995-01-01T00:00:00.000Z",
    "Title" : "A generalized surface echo radar equation for down-looking pencil beam radar.",
    "Series" : "IEICE Trans. Commun.",
    "Volume" : "E78-B",
    "Pages" : "1245-1248"
  }, {
    "Author" : "Marzoug, M. and P. Amayenc",
    "PublicationDate" : "1994-01-01T00:00:00.000Z",
    "Title" : "A class of single- and dual-frequency algorithms for rain rate profiling from a spaceborne radar. Part I: Principle and tests from numerical simulations.",
    "Series" : "J. Atmos. Oceanic Technol.,",
    "Volume" : "11",
    "Pages" : "1480-1506"
  }, {
    "Author" : "Meneghini, R. and K. Nakamura",
    "PublicationDate" : "1990-01-01T00:00:00.000Z",
    "Title" : "Range profiling of the rain rate by an airborne weather radar.",
    "Series" : "Remote Sens. Environ.",
    "Volume" : "31",
    "Pages" : "193-209"
  } ],
  "Quality" : "A Table structure (called Scan Status) is included in the HDF file, containing entries on a scan-by-scan basis.These entries include a geolocation flag and a data quality flag, indicating the percentage of pixels along each scan with values within a pre-defined range.",
  "ISOTopicCategories" : [ "GEOSCIENTIFIC INFORMATION" ],
  "AccessConstraints" : {
    "Description" : "None"
  },
  "RelatedUrls" : [ {
    "URL" : "https://docserver.gesdisc.eosdis.nasa.gov/public/project/Images/TRMM_1C21_7.png",
    "URLContentType" : "VisualizationURL",
    "Type" : "GET RELATED VISUALIZATION"
  }, {
    "Type" : "DATA SET LANDING PAGE",
    "URL" : "https://disc.gsfc.nasa.gov/datacollection/TRMM_1C21_7.html",
    "Description" : "Access the dataset landing page from the GES DISC website.",
    "URLContentType" : "CollectionURL"
  }, {
    "Type" : "GET DATA",
    "Subtype" : "DATA TREE",
    "URL" : "https://disc2.gesdisc.eosdis.nasa.gov/data/TRMM_L1/TRMM_1C21.7",
    "Description" : "Access the data via HTTPS",
    "URLContentType" : "DistributionURL"
  }, {
    "Type" : "USE SERVICE API",
    "Subtype" : "OPENDAP DATA",
    "URL" : "https://disc2.gesdisc.eosdis.nasa.gov/opendap/TRMM_L1/TRMM_1C21.7/",
    "Description" : "Access the data via the OPeNDAP protocol.",
    "URLContentType" : "DistributionURL"
  }, {
    "Type" : "GET DATA",
    "Subtype" : "Earthdata Search",
    "URL" : "https://search.earthdata.nasa.gov/search?q=TRMM_1C21",
    "Description" : "Use the Earthdata Search to find and retrieve data sets across multiple data centers.",
    "URLContentType" : "DistributionURL"
  }, {
    "Type" : "PROJECT HOME PAGE",
    "URL" : "https://trmm.gsfc.nasa.gov/",
    "Description" : "TRMM Project Home Page",
    "URLContentType" : "CollectionURL"
  }, {
    "Type" : "VIEW RELATED INFORMATION",
    "Subtype" : "GENERAL DOCUMENTATION",
    "URL" : "https://pps.gsfc.nasa.gov/Documents/filespec.TRMM.V7.pdf",
    "Description" : "File specification document.",
    "URLContentType" : "PublicationURL"
  }, {
    "Type" : "VIEW RELATED INFORMATION",
    "Subtype" : "GENERAL DOCUMENTATION",
    "URL" : "https://pps.gsfc.nasa.gov/Documents/formatChangesV7.pdf",
    "Description" : "Comparison between TRMM versions 6 and 7.",
    "URLContentType" : "PublicationURL"
  }, {
    "Type" : "VIEW RELATED INFORMATION",
    "Subtype" : "GENERAL DOCUMENTATION",
    "URL" : "http://www.eorc.jaxa.jp/TRMM/documents/PR_algorithm_product_information/pr_manual/PR_Instruction_Manual_V7_L1.pdf",
    "Description" : "TRMM Precipitation Radar Instruction Manual (provided by JAXA)",
    "URLContentType" : "PublicationURL"
  }, {
    "Type" : "VIEW RELATED INFORMATION",
    "Subtype" : "READ-ME",
    "URL" : "https://disc2.gesdisc.eosdis.nasa.gov/data/TRMM_L1/TRMM_1C21/doc/README.TRMM_V7.pdf",
    "Description" : "README Document",
    "URLContentType" : "PublicationURL"
  }, {
    "Type" : "VIEW RELATED INFORMATION",
    "Subtype" : "GENERAL DOCUMENTATION",
    "URL" : "https://gpmweb2https.pps.eosdis.nasa.gov/tsdis/AB/docs/anomalous.html",
    "Description" : "TRMM Data Gaps",
    "URLContentType" : "PublicationURL"
  } ],
  "DataDates" : [ {
    "Date" : "2011-07-01T00:00:00.000Z",
    "Type" : "CREATE"
  }, {
    "Date" : "2016-04-20T00:00:00.000Z",
    "Type" : "UPDATE"
  } ],
  "Abstract" : "The TRMM Precipitation Radar (PR), the first of its kind in space, is an electronically scanning radar, operating at 13.8 GHz that measures the 3-D rainfall distribution over both land and ocean, and defines  the layer depth of the precipitation.\n                                          \nThe 1C21 calculates the effective radar reflectivity factor at 13.8 GHz without any propagation loss (due to rain or any other atmospheric gas) correction (Zm). Therefore, the Zm value can be calculated just by applying a radar equation for volume scatter with PR system parameters. The noise-equivalent Zm is about 21 dBZ. Through the subtraction of the system noise, the Zm value as small as 16 or 18 dBZ are still usable although the data quality is marginal.  In 1C21, all echoes stored in 1B21 are converted to \"dBZ\" unit. This is not relevant for \"non-rain\" echo; however, this policy is adopted so that the 1B21 and 1C21 product format should be as close as possible except for the following points:                                         \n- Radar quantity is Zm in dBZ unit instead of received power (dBm).\n- Data at echo-free range bins judged in 1B21 are replaced with a dummy value.\n\nChanges in horizontal resolution resulting from the TRMM boost that occurred on 24 August 2001:\n\nPre-Boost (before 7 August 2001): Temporal Resolution: 91.5 min/orbit ~ 16 orbits/day; Swath Width: 215 km; Horizontal Resolution: 4.3 km \n\nPost-Boost (after 24 August 2001): Temporal Resolution: 92.5 min/orbit ~ 16 orbits/day; Swath Width: 247 km; Horizontal Resolution: 5.0 km\n",
  "LocationKeywords" : [ {
    "Category" : "GEOGRAPHIC REGION",
    "Type" : "TROPICS"
  } ],
  "MetadataDates" : [ {
    "Date" : "2011-07-15T00:00:00.000Z",
    "Type" : "CREATE"
  }, {
    "Date" : "2019-10-22T14:01:30.000Z",
    "Type" : "UPDATE"
  }, {
    "Date" : "2020-10-31T00:00:00.000Z",
    "Type" : "REVIEW"
  } ],
  "Version" : "7",
  "Projects" : [ {
    "ShortName" : "TRMM",
    "LongName" : "Tropical Rainfall Measuring Mission Project"
  } ],
  "UseConstraints" : {
    "Description" : "The Earth Observing System Data and Information System (EOSDIS) data use policy for NASA data can be accessed at https://earthdata.nasa.gov/earth-observation-data/data-use-policy. For information on how to properly cite and acknowledge data from the NASA GES DISC, refer to https://disc.gsfc.nasa.gov/information/documents?title=data-policy."
  },
  "ContactPersons" : [ {
    "Roles" : [ "Metadata Author" ],
    "FirstName" : "ANDREY",
    "LastName" : "SAVTCHENKO",
    "ContactInformation" : {
      "Addresses" : [ {
        "StreetAddresses" : [ "Distributed Active Archive Center Global Change Data Center", "Code 610.2", "NASA Goddard Space Flight Center" ],
        "City" : "Greenbelt",
        "StateProvince" : "MD",
        "PostalCode" : "20771",
        "Country" : "USA"
      } ],
      "ContactMechanisms" : [ {
        "Type" : "Telephone",
        "Value" : "301-614-5705"
      }, {
        "Type" : "Email",
        "Value" : "Andrey.Savtchenko@nasa.gov"
      } ]
    }
  } ],
  "DataCenters" : [ {
    "Roles" : [ "ARCHIVER" ],
    "ShortName" : "NASA/GSFC/SED/ESD/GCDC/GESDISC",
    "LongName" : "Goddard Earth Sciences Data and Information Services Center (formerly Goddard DAAC), Global Change Data Center, Earth Sciences Division, Science and Exploration Directorate, Goddard Space Flight Center, NASA",
    "ContactInformation" : {
      "RelatedUrls" : [ {
        "URLContentType" : "DataCenterURL",
        "Type" : "HOME PAGE",
        "URL" : "https://disc.gsfc.nasa.gov/",
        "Description" : "NASA GES DISC Website"
      } ]
    },
    "ContactGroups" : [ {
      "Roles" : [ "Data Center Contact" ],
      "GroupName" : "GES DISC HELP DESK SUPPORT GROUP",
      "ContactInformation" : {
        "Addresses" : [ {
          "StreetAddresses" : [ "Goddard Earth Sciences Data and Information Services Center", "Code 610.2", "NASA Goddard Space Flight Center" ],
          "City" : "Greenbelt",
          "StateProvince" : "MD",
          "PostalCode" : "20771",
          "Country" : "USA"
        } ],
        "ContactMechanisms" : [ {
          "Type" : "Telephone",
          "Value" : "301-614-5224"
        }, {
          "Type" : "Fax",
          "Value" : "301-614-5268"
        }, {
          "Type" : "Email",
          "Value" : "gsfc-dl-help-disc@mail.nasa.gov"
        } ]
      }
    } ]
  } ],
  "Platforms" : [ {
    "Type" : "Earth Observation Satellites",
    "ShortName" : "TRMM",
    "LongName" : "Tropical Rainfall Measuring Mission",
    "Instruments" : [ {
      "ShortName" : "PR",
      "LongName" : "TRMM Precipitation Radar"
    } ]
  } ],
  "ArchiveAndDistributionInformation" : {
    "FileDistributionInformation" : [ {
      "FormatType" : "Native",
      "Media" : [ "Online Archive" ],
      "Format" : "HDF",
      "Fees" : "None"
    } ]
  }
}